neurosurfer/__init__.py
neurosurfer/config.py
neurosurfer/diagnostics.py
neurosurfer/logger.py
neurosurfer/version.py
neurosurfer/agents/__init__.py
neurosurfer/agents/sql_agent.py
neurosurfer/agents/tools_router_agent.py
neurosurfer/agents/rag/__init__.py
neurosurfer/agents/rag/agent.py
neurosurfer/agents/rag/config.py
neurosurfer/agents/rag/context_builder.py
neurosurfer/agents/rag/picker.py
neurosurfer/agents/rag/token_utils.py
neurosurfer/agents/react/__init__.py
neurosurfer/agents/react/agent.py
neurosurfer/agents/react/base.py
neurosurfer/agents/react/exceptions.py
neurosurfer/agents/react/history.py
neurosurfer/agents/react/memory.py
neurosurfer/agents/react/parser.py
neurosurfer/agents/react/retry.py
neurosurfer/agents/react/scratchpad.py
neurosurfer/agents/react/types.py
neurosurfer/agents/react/utils.py
neurosurfer/cli/__init__.py
neurosurfer/cli/main.py
neurosurfer/cli/processes.py
neurosurfer/cli/serve.py
neurosurfer/cli/utils.py
neurosurfer/db/__init__.py
neurosurfer/db/sql_database.py
neurosurfer/db/sql_schema_store.py
neurosurfer/examples/quickstart_app.py
neurosurfer/models/chat_models/__init__.py
neurosurfer/models/chat_models/base.py
neurosurfer/models/chat_models/llamacpp.py
neurosurfer/models/chat_models/openai.py
neurosurfer/models/chat_models/transformers.py
neurosurfer/models/chat_models/unsloth.py
neurosurfer/models/embedders/__init__.py
neurosurfer/models/embedders/base.py
neurosurfer/models/embedders/llamacpp.py
neurosurfer/models/embedders/sentence_transformer.py
neurosurfer/rag/__init__.py
neurosurfer/rag/chunker.py
neurosurfer/rag/constants.py
neurosurfer/rag/filereader.py
neurosurfer/rag/ingestor.py
neurosurfer/runtime/checks.py
neurosurfer/runtime/paths.py
neurosurfer/server/__init__.py
neurosurfer/server/app.py
neurosurfer/server/config.py
neurosurfer/server/gunicorn.conf.py
neurosurfer/server/models_registry.py
neurosurfer/server/runtime.py
neurosurfer/server/security.py
neurosurfer/server/api/__init__.py
neurosurfer-0.1.2.dist-info/licenses/LICENSE
neurosurfer-0.1.2.dist-info/licenses/NOTICE
neurosurfer-0.1.2.dist-info/METADATA
neurosurfer-0.1.2.dist-info/WHEEL
neurosurfer-0.1.2.dist-info/entry_points.txt
neurosurfer-0.1.2.dist-info/top_level.txt
neurosurfer-0.1.2.dist-info/RECORD
