Metadata-Version: 2.4
Name: neurosurfer
Version: 0.1.2
Summary: Neurosurfer: production-ready AI agent framework with multi-LLM, RAG, tools, and FastAPI server
Author-email: Nouman Ahsan <naumanhsa965@gmail.com>
Maintainer-email: Nouman Ahsan <naumanhsa965@gmail.com>
License-Expression: Apache-2.0
Project-URL: Homepage, https://naumanhsa.github.io/neurosurfer/
Project-URL: Repository, https://github.com/NaumanHSA/neurosurfer
Project-URL: Issues, https://github.com/NaumanHSA/neurosurfer/issues
Project-URL: Documentation, https://naumanhsa.github.io/neurosurfer/
Keywords: LLM,agents,RAG,transformers,FastAPI,ChromaDB
Classifier: Programming Language :: Python :: 3
Classifier: Operating System :: OS Independent
Classifier: Environment :: GPU
Classifier: Environment :: GPU :: NVIDIA CUDA
Classifier: Topic :: Scientific/Engineering :: Artificial Intelligence
Requires-Python: >=3.9
License-File: LICENSE
License-File: NOTICE
Requires-Dist: fastapi<1.0,>=0.110
Requires-Dist: uvicorn[standard]<1.0,>=0.29
Requires-Dist: gunicorn<24,>=21
Requires-Dist: pydantic<3.0,>=2.6
Requires-Dist: pydantic[email]<3.0,>=2.6
Requires-Dist: pydantic_settings<3.0,>=2.2
Requires-Dist: numpy<3.0,>=1.24
Requires-Dist: pandas<3.0,>=2.1
Requires-Dist: tqdm<5,>=4.66
Requires-Dist: rich<15,>=13
Requires-Dist: itsdangerous<3.0,>=2.1
Requires-Dist: bcrypt<5.0,>=4.1
Requires-Dist: passlib<2.0,>=1.7
Requires-Dist: python-jose[cryptography]<4,>=3.3
Requires-Dist: openai<2.0,>=1.30
Requires-Dist: huggingface_hub<1.0,>=0.20
Requires-Dist: chromadb<2,>=1.0
Requires-Dist: SQLAlchemy<3.0,>=2.0
Requires-Dist: PyMuPDF<2,>=1.23
Requires-Dist: python-docx<2,>=1.0
Requires-Dist: python-pptx<1,>=0.6.21
Requires-Dist: fonttools<5,>=4.43
Requires-Dist: beautifulsoup4<5,>=4.10
Requires-Dist: altair<6,>=5
Requires-Dist: python-magic<0.5,>=0.4; platform_system != "Windows"
Requires-Dist: python-magic-bin<0.5,>=0.4; platform_system == "Windows"
Requires-Dist: typing-extensions<5,>=4.6; python_version < "3.11"
Provides-Extra: torch
Requires-Dist: torch<3.0,>=2.8; extra == "torch"
Requires-Dist: torchvision<0.24,>=0.23; extra == "torch"
Requires-Dist: torchaudio<2.9,>=2.8; extra == "torch"
Requires-Dist: transformers<5.0,>=4.56; extra == "torch"
Requires-Dist: sentence-transformers<6.0,>=5.1; extra == "torch"
Requires-Dist: bitsandbytes<0.49,>=0.48; extra == "torch"
Requires-Dist: unsloth<2026.0,>=2025.10; extra == "torch"
Requires-Dist: accelerate<2.0,>=1.10.1; extra == "torch"
Dynamic: license-file
